Workbook

Sheet READ ME
B2: KAYOS: THE NIGHT OF SILENCE — Asset Bible & Generation Tracker
B3: v1.0 · SC Milenwall · July 2026 · Image generation target: Nano Banana 2
B5: HOW TO USE
B6: 1. Work the ASSETS sheet | C6: Filter by Priority and work P1 (Vertical Slice) first. Copy the full prompt from column H straight into Nano Banana 2.
B7: 2. Update Status as you go | C7: Use the dropdown in column I. The DASHBOARD updates itself. Pipeline: Not Started -> Prompted -> Generated -> Cleaned -> Approved -> In Engine.
B8: 3. 'Cleaned' means the pixel pass | C8: Image models produce near-pixel-art, not true pixel art: grids drift and clusters smear. The reliable pipeline is: generate -> downscale to true size -> clean up in Affinity (Pixel studio) — see the AFFINITY PIPELINE sheet -> export PNG. Budget cleanup time for every sprite/tileset.
B9: 4. Keep a style anchor | C9: Generate CH-001 (Elorin) and PO-001 first, get them right, and then ATTACH those images as references in every later character/portrait generation. Reference images are the #1 consistency tool - prompts alone will drift.
B10: 5. One asset, one session | C10: Generate variants of the same asset in the same chat/session with the reference attached, so the model holds the design.
B12: STATUS LEGEND
B13: Not Started | C13: No prompt run yet.
B14: Prompted | C14: Prompt run, output not yet acceptable (iterate).
B15: Generated | C15: An acceptable raw image exists and is saved to the project folder.
B16: Cleaned | C16: Downscaled + pixel-cleaned; true to grid. See AFFINITY PIPELINE sheet.
B17: Approved | C17: Final look signed off against the style anchors.
B18: In Engine | C18: Imported into Godot, filter=Nearest verified, visible in a scene.
B20: PRIORITY LEGEND
B21: P1 - Vertical Slice | C21: Cold Open + Part One Act I (Starfall). Nothing else matters until these are In Engine.
B22: P2 - Part One | C22: Remainder of Elorin's campaign.
B23: P3 - Part Two | C23: Grakkar's campaign.
B24: P4 - Polish | C24: Visions, endings, aftermath, FX, audio.
B26: NANO BANANA 2 TIPS
B27: Backgrounds | C27: Prompts ask for flat magenta backgrounds on sprites - trivial to key out. If the model ignores it, add 'isolated on solid #FF00FF background' verbatim.
B28: Sprite sheets | C28: If a 4-direction sheet comes out scrambled, generate ONE direction per image instead (edit the prompt to 'walk cycle, facing down, 4 frames in a row') - four clean images beat one messy grid.
B29: Tilesets | C29: Treat tileset outputs as REFERENCE ART: rebuild the actual 32px tiles over them (AFFINITY PIPELINE sheet). Models cannot hold a strict tile grid; don't fight it.
B30: Upscaling | C30: Generate large, then downscale to target size with 'nearest neighbour' - never let an art tool smooth-resize pixel art.
B31: Iteration | C31: Keep the winning image of each asset in a /style_anchors folder. That folder becomes the true art bible.
B33: FILE ORGANISATION (suggested)
B34: assets_raw/ | C34: Raw generations, named by asset ID (CH-001_v3.png).
B35: assets_clean/ | C35: Aseprite-cleaned finals, same IDs - these import to Godot.
B36: style_anchors/ | C36: One winning reference image per character/location.
B38: NOTE ON THE EXAMPLE ROW | C38: Row 2 of ASSETS (CH-001) is pre-filled with example Status/Date/Notes values to show the expected format - reset it to 'Not Started' when you begin.

Sheet DASHBOARD
B2: PRODUCTION DASHBOARD
B4: OVERALL
B5: Total assets | C5: =COUNTA(ASSETS!$A$2:$A$500) -> 129
B6: In Engine (done) | C6: =COUNTIF(ASSETS!$I$2:$I$500,"In Engine") -> 0
B7: % complete | C7: =IF(C5=0,0,C6/C5) -> 0
B9: BY STATUS
B10: Not Started | C10: =COUNTIF(ASSETS!$I$2:$I$500,"Not Started") -> 96
B11: Prompted | C11: =COUNTIF(ASSETS!$I$2:$I$500,"Prompted") -> 0
B12: Generated | C12: =COUNTIF(ASSETS!$I$2:$I$500,"Generated") -> 33
B13: Cleaned | C13: =COUNTIF(ASSETS!$I$2:$I$500,"Cleaned") -> 0
B14: Approved | C14: =COUNTIF(ASSETS!$I$2:$I$500,"Approved") -> 0
B15: In Engine | C15: =COUNTIF(ASSETS!$I$2:$I$500,"In Engine") -> 0
B17: BY CATEGORY
B18: Category | C18: Total | D18: In Engine | E18: % done
B19: Character Sprite | C19: =COUNTIF(ASSETS!$B$2:$B$500,"Character Sprite") -> 28 | D19: =COUNTIFS(ASSETS!$B$2:$B$500,"Character Sprite",ASSETS!$I$2:$I$500,"In Engine") -> 0 | E19: =IF(C19=0,0,D19/C19) -> 0
B20: Portrait | C20: =COUNTIF(ASSETS!$B$2:$B$500,"Portrait") -> 14 | D20: =COUNTIFS(ASSETS!$B$2:$B$500,"Portrait",ASSETS!$I$2:$I$500,"In Engine") -> 0 | E20: =IF(C20=0,0,D20/C20) -> 0
B21: Environment | C21: =COUNTIF(ASSETS!$B$2:$B$500,"Environment") -> 16 | D21: =COUNTIFS(ASSETS!$B$2:$B$500,"Environment",ASSETS!$I$2:$I$500,"In Engine") -> 0 | E21: =IF(C21=0,0,D21/C21) -> 0
B22: Prop / Object | C22: =COUNTIF(ASSETS!$B$2:$B$500,"Prop / Object") -> 24 | D22: =COUNTIFS(ASSETS!$B$2:$B$500,"Prop / Object",ASSETS!$I$2:$I$500,"In Engine") -> 0 | E22: =IF(C22=0,0,D22/C22) -> 0
B23: Item Icon | C23: =COUNTIF(ASSETS!$B$2:$B$500,"Item Icon") -> 16 | D23: =COUNTIFS(ASSETS!$B$2:$B$500,"Item Icon",ASSETS!$I$2:$I$500,"In Engine") -> 0 | E23: =IF(C23=0,0,D23/C23) -> 0
B24: UI | C24: =COUNTIF(ASSETS!$B$2:$B$500,"UI") -> 18 | D24: =COUNTIFS(ASSETS!$B$2:$B$500,"UI",ASSETS!$I$2:$I$500,"In Engine") -> 0 | E24: =IF(C24=0,0,D24/C24) -> 0
B25: Story Panel | C25: =COUNTIF(ASSETS!$B$2:$B$500,"Story Panel") -> 10 | D25: =COUNTIFS(ASSETS!$B$2:$B$500,"Story Panel",ASSETS!$I$2:$I$500,"In Engine") -> 0 | E25: =IF(C25=0,0,D25/C25) -> 0
B26: Font / External | C26: =COUNTIF(ASSETS!$B$2:$B$500,"Font / External") -> 3 | D26: =COUNTIFS(ASSETS!$B$2:$B$500,"Font / External",ASSETS!$I$2:$I$500,"In Engine") -> 0 | E26: =IF(C26=0,0,D26/C26) -> 0
B28: BY PRIORITY
B29: Priority | C29: Total | D29: In Engine | E29: % done
B30: P1 - Vertical Slice | C30: =COUNTIF(ASSETS!$E$2:$E$500,"P1 - Vertical Slice") -> 33 | D30: =COUNTIFS(ASSETS!$E$2:$E$500,"P1 - Vertical Slice",ASSETS!$I$2:$I$500,"In Engine") -> 0 | E30: =IF(C30=0,0,D30/C30) -> 0
B31: P2 - Part One | C31: =COUNTIF(ASSETS!$E$2:$E$500,"P2 - Part One") -> 50 | D31: =COUNTIFS(ASSETS!$E$2:$E$500,"P2 - Part One",ASSETS!$I$2:$I$500,"In Engine") -> 0 | E31: =IF(C31=0,0,D31/C31) -> 0
B32: P3 - Part Two | C32: =COUNTIF(ASSETS!$E$2:$E$500,"P3 - Part Two") -> 37 | D32: =COUNTIFS(ASSETS!$E$2:$E$500,"P3 - Part Two",ASSETS!$I$2:$I$500,"In Engine") -> 0 | E32: =IF(C32=0,0,D32/C32) -> 0
B33: P4 - Polish | C33: =COUNTIF(ASSETS!$E$2:$E$500,"P4 - Polish") -> 9 | D33: =COUNTIFS(ASSETS!$E$2:$E$500,"P4 - Polish",ASSETS!$I$2:$I$500,"In Engine") -> 0 | E33: =IF(C33=0,0,D33/C33) -> 0

Sheet AFFINITY PIPELINE
B2: AFFINITY PIPELINE — pixel-art cleanup on the unified Affinity app (macOS)
B3: For: Affinity by Canva (unified app — Pixel / Vector / Layout studios), iMac M4. Shortcuts given Mac-style (Cmd).
B5: THE VERDICT FIRST
B6: Affinity replaces Aseprite for most of this bible | C6: Affinity's Pixel studio is a full raster editor (it is the old Affinity Photo). It can do everything a pixel cleanup pass needs: hard aliased pixels, nearest-neighbour resampling, exact canvases, palettes, PNG export. Use it.
B7: The one real gap: animation | C7: Affinity has NO frame timeline and NO onion skinning. Aseprite's whole reason to exist is animating sprites. For the 28 character sprite sheets (4-direction walk cycles), you can still lay frames out manually on a grid in Affinity — you just can't PREVIEW the animation without exporting and running it in Godot.
B8: My recommendation | C8: Do everything in Affinity. Do NOT buy a second tool yet. Character walk cycles are Phase 6 work — months away. If the no-preview friction actually bites when you get there, add Aseprite (~USD $20) or LibreSprite (free fork) THEN, for sprite sheets only. Don't pre-solve a problem you haven't hit.
B9: Where Affinity is genuinely BETTER than Aseprite | C9: Portraits (PO-001..014), story panels (VS-001..010), all UI (UI-001..018), and the logo. These are painterly or vector work — Aseprite is bad at them, Affinity is excellent. Also: cleaning up raw AI generations (keying out magenta, colour correction, palette unification) is far better in Affinity.
B11: ONE-TIME APP SETUP
B12: 1. Work in the Pixel studio | C12: Switch studios from the selector at the top of the window: Pixel / Vector / Layout. Pixel = the old Affinity Photo = where all sprite/tile cleanup happens. Use Vector studio only for UI panels, icons and the logo.
B13: 2. Turn on Pixel View | C13: Cmd+Opt+Y toggles Pixel View / Vector View. Pixel View shows true rasterised pixels — this is the one you want for all pixel work. (If your art ever looks mysteriously soft, you've flipped to Vector View.)
B14: 3. Set up the grid | C14: Turn on the grid and set spacing to 32 px with 1 division (View menu > grid settings; in the unified app it sits under the View/Guides area). This is your tile grid for every environment and prop sheet.
B15: 4. Turn on snapping | C15: Snapping toggle lives in the toolbar. With Force Pixel Alignment on (Vector studio toolbar), vector shapes land on whole pixels instead of half-pixel mush — essential when building UI that must sit on a 640x360 screen.
B16: 5. Save a KAYOS palette | C16: In the Swatches panel, create a new Document Palette per faction: Noctari (indigo/violet/silver), Solari (gold/ivory/white/dawn-orange), Orc (ash/iron/rust/ember). Build them once from your approved style anchors, then every later asset picks from them. This is how a 129-asset game stays visually coherent.
B18: CANVAS SETUP PER ASSET TYPE
B19: Character sprite frame | C19: 48 x 72 px · 72 DPI · RGB/8 · transparent. Sheet = 4 cols x 4 rows = 192 x 288 px. Feet on the frame's bottom edge. Character height varies by race (see SPRITE SCALE sheet) — Elorin/elves/humans 64 px, orcs 68-70 px, Terran 52 px, children 44 px.
B20: Tileset working canvas | C20: Multiple of 32. Suggested 512 x 512 px (16x16 tiles) · 72 DPI · RGB/8.
B21: Prop / object | C21: Multiples of 32 (32x32, 64x64, 96x64 etc) · transparent background.
B22: Item icon | C22: Exactly 32 x 32 px · transparent.
B23: UI element | C23: Build in VECTOR studio at 2x target size, export at 1x and 2x. 9-slice panels: design the corners at 8-16px so they survive scaling.
B24: Portrait | C24: 512 x 512 px working (painterly, Pixel studio), export a 96 x 96 game version.
B25: Story panel | C25: 1920 x 1080 px · painterly · NOT pixel art (deliberate register shift).
B26: Always | C26: 72 DPI, RGB/8-bit, sRGB. DPI is irrelevant to games but keep it consistent so nothing silently rescales.
B28: TOOLS: USE THESE / AVOID THESE
B29: USE: Pixel Tool | C29: Draws hard, aliased, single pixels. This is THE tool for cleanup. Set width to 1 px.
B30: USE: Flood Fill Tool | C30: Turn anti-aliasing OFF in its options bar before using, or you'll get soft fringe pixels.
B31: USE: Selection tools + Cmd+C/V | C31: Copy-paste is how you build walk-cycle frames: duplicate the idle frame, nudge limbs, repeat.
B32: USE: Colour Picker | C32: Pick from your saved palette constantly. Never introduce a colour that isn't in the faction palette.
B33: AVOID: Paint Brush Tool | C33: It is anti-aliased by design — it will feather your edges and silently destroy pixel art.
B34: AVOID: any Blur / Feather / Soft Shadow / Glow effect | C34: All of them produce in-between pixels. Shade with dithering or discrete colour steps instead.
B35: AVOID: free-transform scaling of pixel layers | C35: Scaling a pixel layer by a non-integer amount resamples it. If you must scale, use whole multiples only.
B36: AVOID: Layer FX / Live Filters on sprites | C36: Fine on portraits and story panels. Fatal on 32px sprites.
B38: THE CLEANUP WORKFLOW (raw generation -> final PNG)
B39: Step 1 — open the raw generation | C39: Open the Nano Banana 2 output in Pixel studio. It will be large (1024px+) and only NEAR pixel art: drifting grid, smeared clusters, anti-aliased edges.
B40: Step 2 — key out the magenta | C40: Select > Select Sampled Colour on the flat magenta background, tolerance low, then delete. (Or Select > Colour Range.) This is why every sprite prompt asks for flat magenta.
B41: Step 3 — downscale with Nearest Neighbour | C41: Document menu > Resize Document. Set target size (e.g. 48 x 72). Set Resampling = NEAREST NEIGHBOUR. Never Bilinear/Bicubic/Lanczos — those blur. NOTE: in the unified app the resize options are still under Document while in Pixel studio, but sit deeper in the menu than they did in v2 — hunt for them once, then remember.
B42: Step 3b — ignore 'Pixel Art' resize | C42: Affinity has a separate 'Pixel Art' resizing option (XBR/HQX, 2x/3x/4x). That's for ENLARGING existing pixel art. It is not what we want here — we're downscaling. Nearest Neighbour is the correct choice.
B43: Step 4 — the actual cleanup (the real work) | C43: At 48x72 the downscale will be a mess. Zoom to 800-1600%, and with the Pixel Tool redraw: fix the silhouette first (it must read instantly at native size), then flatten stray in-between colours onto palette colours, then clean the outline to a single consistent pixel run. Budget 20-45 min per sprite. This is normal and unavoidable.
B44: Step 5 — check at native size | C44: Keep a second view at 100% zoom (Window > New View) while you work at 1600%. If it doesn't read at 100%, it doesn't work — no amount of detail fixes a bad silhouette.
B45: Step 6 — export | C45: File > Export > PNG. Confirm size is exact and resampling is Nearest Neighbour (or 'Don't resample'). Save to assets_clean/ using the asset ID (CH-001.png). Then set Status = Cleaned.
B46: Step 7 — into Godot | C46: Import, then in the Import tab set Filter = OFF / Nearest and re-import. If your sprite looks blurry in-engine, this is always the cause. Then set Status = In Engine.
B48: TILESETS — THE SPECIAL CASE
B49: Treat AI tileset output as reference only | C49: No image model can hold a strict 32px grid. Do not try to salvage the grid — you'll lose hours.
B50: The method | C50: Open the generation as a BOTTOM layer, drop opacity to ~40%, turn on the 32px grid, then draw clean tiles on a new layer above it using the generation purely as colour/mood reference. You are tracing intent, not pixels.
B51: Affinity gap: no tiled preview | C51: Aseprite can preview a tile repeating seamlessly; Affinity can't. Workaround: build the tile, then copy-paste it into a 3x3 block on a scratch layer to eyeball the seams. Crude but it works.
B53: SPRITE SHEETS — THE ANIMATION WORKAROUND
B54: Layout | C54: One canvas, 192 x 288 px. Each 48x72 cell = one frame. Row 1 = walk down, row 2 = up, row 3 = left, row 4 = right.
B55: Build method | C55: Draw the idle/contact frame. Duplicate the layer, nudge the legs/arms 1-2 px, repeat for 4 frames. Keep each frame on its own layer group so you can revise one without touching the others.
B56: No onion skin — the workaround | C56: Set the previous frame's layer to ~30% opacity underneath the one you're drawing. That IS onion skinning, done manually. Toggle it off before export.
B57: No playback — the workaround | C57: Export the sheet and preview the animation in Godot (AnimatedSprite2D). Slower loop than Aseprite, but it's the only place the animation has to look right anyway.
B58: If this becomes painful | C58: That's the signal to add Aseprite/LibreSprite for sprite sheets only — and only then.
B60: PALETTE DISCIPLINE (the thing that makes it look like ONE game)
B61: Rule | C61: Every asset picks colours ONLY from its faction's document palette. No exceptions, no 'close enough' colours.
B62: Why it matters more than detail | C62: 129 assets made by an image model will drift wildly in hue. A unified palette is what makes them read as one world — it does more for coherence than any amount of per-sprite polish.
B63: Build the palettes from the anchors | C63: Generate CH-001 (Elorin) and PO-001 first. Approve them. Pull the palette from those images (Swatches > create palette from image), prune to ~16-24 colours per faction, and lock it. Everything after conforms.

Sheet SPRITE SCALE
A1: Character group | B1: Height in frame | C1: Assets
A2: Children | B2: ~44 px | C2: CH-028
A3: Terran (Durak) | B3: ~52 px (broad) | C3: CH-011
A4: Elves & humans | B4: ~62-64 px | C4: CH-001/002, CH-006-010, CH-012-018, CH-023-027
A5: Void Wardens (armoured) | B5: ~68 px | C5: CH-017
A6: Orcs | B6: ~68-70 px | C6: CH-003/004/005, CH-019-022, CH-028 (adult)
A8: FRAME SPEC (locked 2026-07-17)
A9: Sprite frame | B9: 48 x 72 px | C9: 48 px width confirmed sufficient by the user, 2026-07-17.
A10: Sprite sheet | B10: 192 x 288 px | C10: 4 columns x 4 rows.
A11: Row order | B11: 0=down 1=up 2=right 3=left | C11: Lock this. Confirmed against the cleaned CH-001 sheet 2026-07-17 - the art is the ground truth here, not the other way round.
A12: Baseline | B12: Feet on the frame's bottom edge | C12: Headroom varies; the feet do not.
A13: Tile grid | B13: 32 x 32 px | C13: Tilesets ONLY. Nothing to do with sprite frames.
A15: REFERENCE
A16: CH-001 (Elorin) | B16: 64 px tall in a 48x72 frame | C16: Already produced. Every other elf/human matches her. Do not re-derive this from anything else.
A18: Native viewport is 960 x 540 (GDD S13). | C18: Never judge sprite size in Affinity at 100%. The only honest size check is running the sheet in Godot.

Sheet ASSETS
A1: ID | B1: Category | C1: Asset Name | D1: Used In | E1: Priority | F1: Size / Format | G1: Variants & Animations | H1: Nano Banana 2 Prompt (copy whole cell) | I1: Status | J1: Date Done | K1: Notes
A2: CH-001 | B2: Character Sprite | C2: Elorin Voidweaver (Academy) | D2: P1 all acts | E2: P1 - Vertical Slice | F2: 48x72/frame · 192x288 sheet (4x4) | G2: 3 class palette variants (Voidweaver indigo-black / Harmonist silver-blue / Mender pale green) | H2: HD pixel art character sprite sheet for a top-down 2D dark-fantasy RPG (Zelda: Minish Cap fidelity, 48x72 px per frame). Grid layout: 4 rows = walk down / up / left / right, exactly 4 frames per row (walk cycle: contact-pass-contact-pass), 4 rows only, no extra columns. A Noctari night elf woman, mid-life scholar-archmage: long dark hair, elegant layered academy robes with subtle void-black trim, calm intense bearing. Noctari (night elf) palette: deep indigo, violet, silver starlight accents. Clean readable silhouette, crisp pixel clusters, no anti-aliasing, unified palette, flat solid magenta background for easy removal. | I2: Generated | J2: 2026-07-12 | K2: (EXAMPLE ROW - reset to Not Started) v3 kept; anchor saved to style_anchors/.
A3: CH-002 | B3: Character Sprite | C3: Elorin (exile / travel) | D3: P1 Act III | E3: P2 - Part One | F3: 48x72/frame · 192x288 sheet (4x4) | G3: - | H3: HD pixel art character sprite sheet for a top-down 2D dark-fantasy RPG (Zelda: Minish Cap fidelity, 48x72 px per frame). Grid layout: 4 rows = walk down / up / left / right, exactly 4 frames per row (walk cycle: contact-pass-contact-pass), 4 rows only, no extra columns. Same Noctari woman as CH-001 but in a hooded weathered travel cloak, worn satchel, wearier posture. Noctari (night elf) palette: deep indigo, violet, silver starlight accents. Clean readable silhouette, crisp pixel clusters, no anti-aliasing, unified palette, flat solid magenta background for easy removal. | I3: Not Started | K3: Use CH-001 output as reference image for consistency.
A4: CH-003 | B4: Character Sprite | C4: Grakkar (young, Ashpile) | D4: P2 Act I | E4: P3 - Part Two | F4: 48x72/frame · 192x288 sheet (4x4) | G4: - | H4: HD pixel art character sprite sheet for a top-down 2D dark-fantasy RPG (Zelda: Minish Cap fidelity, 48x72 px per frame). Grid layout: 4 rows = walk down / up / left / right, exactly 4 frames per row (walk cycle: contact-pass-contact-pass), 4 rows only, no extra columns. A young orc labor-slave: lean but broad, ragged work clothes, iron collar, watchful intelligent eyes. orc/Ashpile palette: ash grey, iron, rust, ember orange. Clean readable silhouette, crisp pixel clusters, no anti-aliasing, unified palette, flat solid magenta background for easy removal. | I4: Not Started
A5: CH-004 | B5: Character Sprite | C5: Grakkar (prime, facility) | D5: P2 Act II | E5: P3 - Part Two | F5: 48x72/frame · 192x288 sheet (4x4) | G5: Variant: archive disguise robes | H5: HD pixel art character sprite sheet for a top-down 2D dark-fantasy RPG (Zelda: Minish Cap fidelity, 48x72 px per frame). Grid layout: 4 rows = walk down / up / left / right, exactly 4 frames per row (walk cycle: contact-pass-contact-pass), 4 rows only, no extra columns. The same orc in his prime: massive, scarred, controlled, plain laborer garb concealing discipline. orc/Ashpile palette: ash grey, iron, rust, ember orange. Clean readable silhouette, crisp pixel clusters, no anti-aliasing, unified palette, flat solid magenta background for easy removal. | I5: Not Started | K5: Reference CH-003 output for facial continuity.
A6: CH-005 | B6: Character Sprite | C6: Grakkar the Unbound (the Night) | D6: P2 Act III | E6: P3 - Part Two | F6: 48x72/frame · 192x288 sheet (4x4) | G6: - | H6: HD pixel art character sprite sheet for a top-down 2D dark-fantasy RPG (Zelda: Minish Cap fidelity, 48x72 px per frame). Grid layout: 4 rows = walk down / up / left / right, exactly 4 frames per row (walk cycle: contact-pass-contact-pass), 4 rows only, no extra columns. The same orc as a scarred elder revolutionary: grey-streaked, upright, terrible resolve, dark leathers. orc/Ashpile palette: ash grey, iron, rust, ember orange. Clean readable silhouette, crisp pixel clusters, no anti-aliasing, unified palette, flat solid magenta background for easy removal. | I6: Not Started
A7: CH-006 | B7: Character Sprite | C7: Talindir (apprentice scribe) | D7: Cold Open, P1 | E7: P1 - Vertical Slice | F7: 48x72/frame · 192x288 sheet (4x4) | G7: - | H7: HD pixel art character sprite sheet for a top-down 2D dark-fantasy RPG (Zelda: Minish Cap fidelity, 48x72 px per frame). Grid layout: 4 rows = walk down / up / left / right, exactly 4 frames per row (walk cycle: contact-pass-contact-pass), 4 rows only, no extra columns. A young-looking elf apprentice scribe (~80, youthful for an elf): ink-stained fingers, satchel of scrolls, modest grey-blue robes. Noctari (night elf) palette: deep indigo, violet, silver starlight accents. Clean readable silhouette, crisp pixel clusters, no anti-aliasing, unified palette, flat solid magenta background for easy removal. | I7: Generated
A8: CH-007 | B8: Character Sprite | C8: Talindir (the Night / coda) | D8: Cold Open, Coda | E8: P1 - Vertical Slice | F8: 48x72/frame · 192x288 sheet (4x4) | G8: - | H8: HD pixel art character sprite sheet for a top-down 2D dark-fantasy RPG (Zelda: Minish Cap fidelity, 48x72 px per frame). Grid layout: 4 rows = walk down / up / left / right, exactly 4 frames per row (walk cycle: contact-pass-contact-pass), 4 rows only, no extra columns. The same elf scribe aged and hollowed by catastrophe: dishevelled robes, clutching a chronicle ledger, haunted but resolute. Muted grey-violet palette. Clean readable silhouette, crisp pixel clusters, no anti-aliasing, unified palette, flat solid magenta background for easy removal. | I8: Generated
A9: CH-008 | B9: Character Sprite | C9: Sera (structural enchantress) | D9: P1 | E9: P1 - Vertical Slice | F9: 48x72/frame · 192x288 sheet (4x4) | G9: - | H9: HD pixel art character sprite sheet for a top-down 2D dark-fantasy RPG (Zelda: Minish Cap fidelity, 48x72 px per frame). Grid layout: 4 rows = walk down / up / left / right, exactly 4 frames per row (walk cycle: contact-pass-contact-pass), 4 rows only, no extra columns. A Solari sun elf woman, precise and immaculate: structured gold-white work robes, tool sash of enchanting instruments. Solari (sun elf) palette: radiant gold, ivory, white marble, dawn-orange accents. Clean readable silhouette, crisp pixel clusters, no anti-aliasing, unified palette, flat solid magenta background for easy removal. | I9: Generated
A10: CH-009 | B10: Character Sprite | C10: Coil (Noctari theorist) | D10: P1 | E10: P1 - Vertical Slice | F10: 48x72/frame · 192x288 sheet (4x4) | G10: - | H10: HD pixel art character sprite sheet for a top-down 2D dark-fantasy RPG (Zelda: Minish Cap fidelity, 48x72 px per frame). Grid layout: 4 rows = walk down / up / left / right, exactly 4 frames per row (walk cycle: contact-pass-contact-pass), 4 rows only, no extra columns. A wiry Noctari man, Elorin's former student: rumpled scholar robes, spectacles, armful of notes, nervous energy. Noctari (night elf) palette: deep indigo, violet, silver starlight accents. Clean readable silhouette, crisp pixel clusters, no anti-aliasing, unified palette, flat solid magenta background for easy removal. | I10: Generated
A11: CH-010 | B11: Character Sprite | C11: Vara (human prodigy) | D11: P1 | E11: P1 - Vertical Slice | F11: 48x72/frame · 192x288 sheet (4x4) | G11: - | H11: HD pixel art character sprite sheet for a top-down 2D dark-fantasy RPG (Zelda: Minish Cap fidelity, 48x72 px per frame). Grid layout: 4 rows = walk down / up / left / right, exactly 4 frames per row (walk cycle: contact-pass-contact-pass), 4 rows only, no extra columns. A young human woman prodigy among elves: simple practical clothes, bright alert posture, slightly out of place. Warm earth-tone palette against elven surroundings. Clean readable silhouette, crisp pixel clusters, no anti-aliasing, unified palette, flat solid magenta background for easy removal. | I11: Generated
A12: CH-011 | B12: Character Sprite | C12: Durak Ironthought (Terran geomancer) | D12: P1 | E12: P2 - Part One | F12: 48x72/frame · 192x288 sheet (4x4) | G12: - | H12: HD pixel art character sprite sheet for a top-down 2D dark-fantasy RPG (Zelda: Minish Cap fidelity, 48x72 px per frame). Grid layout: 4 rows = walk down / up / left / right, exactly 4 frames per row (walk cycle: contact-pass-contact-pass), 4 rows only, no extra columns. A stout Terran (dwarf-like earthfolk) geomancer: stone-grey skin, braided beard with copper rings, heavy tool harness, rune-etched chisels. Clean readable silhouette, crisp pixel clusters, no anti-aliasing, unified palette, flat solid magenta background for easy removal. | I12: Not Started
A13: CH-012 | B13: Character Sprite | C13: Seravin Hollow-Water (mentor) | D13: P1 memory scenes | E13: P2 - Part One | F13: 48x72/frame · 192x288 sheet (4x4) | G13: - | H13: HD pixel art character sprite sheet for a top-down 2D dark-fantasy RPG (Zelda: Minish Cap fidelity, 48x72 px per frame). Grid layout: 4 rows = walk down / up / left / right, exactly 4 frames per row (walk cycle: contact-pass-contact-pass), 4 rows only, no extra columns. An elderly Noctari mentor: serene, water-smooth robes in fading blues, walking staff, gentle gravity. Noctari (night elf) palette: deep indigo, violet, silver starlight accents. Clean readable silhouette, crisp pixel clusters, no anti-aliasing, unified palette, flat solid magenta background for easy removal. | I13: Not Started
A14: CH-013 | B14: Character Sprite | C14: Corel (containment archmagister) | D14: P1 | E14: P2 - Part One | F14: 48x72/frame · 192x288 sheet (4x4) | G14: - | H14: HD pixel art character sprite sheet for a top-down 2D dark-fantasy RPG (Zelda: Minish Cap fidelity, 48x72 px per frame). Grid layout: 4 rows = walk down / up / left / right, exactly 4 frames per row (walk cycle: contact-pass-contact-pass), 4 rows only, no extra columns. An exhausted Noctari archmagister: formal high-collared robes gone slightly unkempt, dark-ringed eyes, burden visible in the shoulders. Noctari (night elf) palette: deep indigo, violet, silver starlight accents. Clean readable silhouette, crisp pixel clusters, no anti-aliasing, unified palette, flat solid magenta background for easy removal. | I14: Not Started
A15: CH-014 | B15: Character Sprite | C15: Conclave official (generic) | D15: P1 | E15: P2 - Part One | F15: 48x72/frame · 192x288 sheet (4x4) | G15: 2 color variants | H15: HD pixel art character sprite sheet for a top-down 2D dark-fantasy RPG (Zelda: Minish Cap fidelity, 48x72 px per frame). Grid layout: 4 rows = walk down / up / left / right, exactly 4 frames per row (walk cycle: contact-pass-contact-pass), 4 rows only, no extra columns. A haughty elven Conclave official: ceremonial layered robes, chain of office, imperious bearing. Mixed Noctari/Solari court palette. Clean readable silhouette, crisp pixel clusters, no anti-aliasing, unified palette, flat solid magenta background for easy removal. | I15: Not Started
A16: CH-015 | B16: Character Sprite | C16: Academy student set | D16: P1 | E16: P1 - Vertical Slice | F16: 48x72/frame · 192x288 sheet (4x4) | G16: 3 body/hair variants | H16: HD pixel art character sprite sheet for a top-down 2D dark-fantasy RPG (Zelda: Minish Cap fidelity, 48x72 px per frame). Grid layout: 4 rows = walk down / up / left / right, exactly 4 frames per row (walk cycle: contact-pass-contact-pass), 4 rows only, no extra columns. Young elven academy students in matching study robes with house-color sashes. Noctari (night elf) palette: deep indigo, violet, silver starlight accents. Clean readable silhouette, crisp pixel clusters, no anti-aliasing, unified palette, flat solid magenta background for easy removal. | I16: Generated | K16: Crowd filler for Starfall.
A17: CH-016 | B17: Character Sprite | C17: Academy researcher (generic) | D17: P1 | E17: P2 - Part One | F17: 48x72/frame · 192x288 sheet (4x4) | G17: 2 variants | H17: HD pixel art character sprite sheet for a top-down 2D dark-fantasy RPG (Zelda: Minish Cap fidelity, 48x72 px per frame). Grid layout: 4 rows = walk down / up / left / right, exactly 4 frames per row (walk cycle: contact-pass-contact-pass), 4 rows only, no extra columns. Mid-rank elven researcher: work robes with protective apron, glyph-marked gloves. Noctari (night elf) palette: deep indigo, violet, silver starlight accents. Clean readable silhouette, crisp pixel clusters, no anti-aliasing, unified palette, flat solid magenta background for easy removal. | I17: Not Started
A18: CH-017 | B18: Character Sprite | C18: Void Warden | D18: P1 Act III, P2 Act III | E18: P2 - Part One | F18: 48x72/frame · 192x288 sheet (4x4) | G18: - | H18: HD pixel art character sprite sheet for a top-down 2D dark-fantasy RPG (Zelda: Minish Cap fidelity, 48x72 px per frame). Grid layout: 4 rows = walk down / up / left / right, exactly 4 frames per row (walk cycle: contact-pass-contact-pass), 4 rows only, no extra columns. An elite vault guardian in sealed dark plate armor chased with silver null-glyphs, faceless helm, halberd of black glass. Intimidating silhouette. Clean readable silhouette, crisp pixel clusters, no anti-aliasing, unified palette, flat solid magenta background for easy removal. | I18: Not Started | K18: Appears in BOTH parts - the vault's constant.
A19: CH-018 | B19: Character Sprite | C19: Starfall citizen set | D19: P1 | E19: P2 - Part One | F19: 48x72/frame · 192x288 sheet (4x4) | G19: 4 variants (mixed ages) | H19: HD pixel art character sprite sheet for a top-down 2D dark-fantasy RPG (Zelda: Minish Cap fidelity, 48x72 px per frame). Grid layout: 4 rows = walk down / up / left / right, exactly 4 frames per row (walk cycle: contact-pass-contact-pass), 4 rows only, no extra columns. Ordinary Noctari city folk: merchants, lamplighters, parents, elders. Noctari (night elf) palette: deep indigo, violet, silver starlight accents. Clean readable silhouette, crisp pixel clusters, no anti-aliasing, unified palette, flat solid magenta background for easy removal. | I19: Not Started
A20: CH-019 | B20: Character Sprite | C20: Morga Steelheart | D20: P2 | E20: P3 - Part Two | F20: 48x72/frame · 192x288 sheet (4x4) | G20: - | H20: HD pixel art character sprite sheet for a top-down 2D dark-fantasy RPG (Zelda: Minish Cap fidelity, 48x72 px per frame). Grid layout: 4 rows = walk down / up / left / right, exactly 4 frames per row (walk cycle: contact-pass-contact-pass), 4 rows only, no extra columns. An orc woman elder, the revolution's conscience: iron-grey braids, patched war-coat, carries herself like a judge. orc/Ashpile palette: ash grey, iron, rust, ember orange. Clean readable silhouette, crisp pixel clusters, no anti-aliasing, unified palette, flat solid magenta background for easy removal. | I20: Not Started
A21: CH-020 | B21: Character Sprite | C21: Kess | D21: P2 | E21: P3 - Part Two | F21: 48x72/frame · 192x288 sheet (4x4) | G21: - | H21: HD pixel art character sprite sheet for a top-down 2D dark-fantasy RPG (Zelda: Minish Cap fidelity, 48x72 px per frame). Grid layout: 4 rows = walk down / up / left / right, exactly 4 frames per row (walk cycle: contact-pass-contact-pass), 4 rows only, no extra columns. A young orc courier/agent: quick, slight for an orc, hooded wrap, message tubes at the belt. orc/Ashpile palette: ash grey, iron, rust, ember orange. Clean readable silhouette, crisp pixel clusters, no anti-aliasing, unified palette, flat solid magenta background for easy removal. | I21: Not Started
A22: CH-021 | B22: Character Sprite | C22: Orc laborer set | D22: P2 | E22: P3 - Part Two | F22: 48x72/frame · 192x288 sheet (4x4) | G22: 3 variants | H22: HD pixel art character sprite sheet for a top-down 2D dark-fantasy RPG (Zelda: Minish Cap fidelity, 48x72 px per frame). Grid layout: 4 rows = walk down / up / left / right, exactly 4 frames per row (walk cycle: contact-pass-contact-pass), 4 rows only, no extra columns. Enslaved orc laborers: iron collars, tool harnesses, ash-dusted work clothes, weary strength. orc/Ashpile palette: ash grey, iron, rust, ember orange. Clean readable silhouette, crisp pixel clusters, no anti-aliasing, unified palette, flat solid magenta background for easy removal. | I22: Not Started
A23: CH-022 | B23: Character Sprite | C23: Orc rebel fighter | D23: P2 Act I (Black Crag) | E23: P3 - Part Two | F23: 48x72/frame · 192x288 sheet (4x4) | G23: 2 variants | H23: HD pixel art character sprite sheet for a top-down 2D dark-fantasy RPG (Zelda: Minish Cap fidelity, 48x72 px per frame). Grid layout: 4 rows = walk down / up / left / right, exactly 4 frames per row (walk cycle: contact-pass-contact-pass), 4 rows only, no extra columns. Orc rebellion fighter: improvised armor from labor gear, broken-chain motif painted on chest. orc/Ashpile palette: ash grey, iron, rust, ember orange. Clean readable silhouette, crisp pixel clusters, no anti-aliasing, unified palette, flat solid magenta background for easy removal. | I23: Not Started
A24: CH-023 | B24: Character Sprite | C24: Elven overseer | D24: P2 | E24: P3 - Part Two | F24: 48x72/frame · 192x288 sheet (4x4) | G24: - | H24: HD pixel art character sprite sheet for a top-down 2D dark-fantasy RPG (Zelda: Minish Cap fidelity, 48x72 px per frame). Grid layout: 4 rows = walk down / up / left / right, exactly 4 frames per row (walk cycle: contact-pass-contact-pass), 4 rows only, no extra columns. A cold elven labor overseer: crisp uniform coat, glyph-tipped rod of office, contemptuous posture. Solari (sun elf) palette: radiant gold, ivory, white marble, dawn-orange accents. Clean readable silhouette, crisp pixel clusters, no anti-aliasing, unified palette, flat solid magenta background for easy removal. | I24: Not Started
A25: CH-024 | B25: Character Sprite | C25: Facility researcher (Solari) | D25: P2 | E25: P3 - Part Two | F25: 48x72/frame · 192x288 sheet (4x4) | G25: 2 variants | H25: HD pixel art character sprite sheet for a top-down 2D dark-fantasy RPG (Zelda: Minish Cap fidelity, 48x72 px per frame). Grid layout: 4 rows = walk down / up / left / right, exactly 4 frames per row (walk cycle: contact-pass-contact-pass), 4 rows only, no extra columns. Solari facility researcher: pristine work robes, clipboard scroll-frame, oblivious to the labor around them. Solari (sun elf) palette: radiant gold, ivory, white marble, dawn-orange accents. Clean readable silhouette, crisp pixel clusters, no anti-aliasing, unified palette, flat solid magenta background for easy removal. | I25: Not Started
A26: CH-025 | B26: Character Sprite | C26: Archivist of Astral Wisdom | D26: P2 | E26: P3 - Part Two | F26: 48x72/frame · 192x288 sheet (4x4) | G26: - | H26: HD pixel art character sprite sheet for a top-down 2D dark-fantasy RPG (Zelda: Minish Cap fidelity, 48x72 px per frame). Grid layout: 4 rows = walk down / up / left / right, exactly 4 frames per row (walk cycle: contact-pass-contact-pass), 4 rows only, no extra columns. An ancient elven archivist: dust-colored robes, key-ring of dozens of archive keys, lantern-staff. Solari (sun elf) palette: radiant gold, ivory, white marble, dawn-orange accents. Clean readable silhouette, crisp pixel clusters, no anti-aliasing, unified palette, flat solid magenta background for easy removal. | I26: Not Started
A27: CH-026 | B27: Character Sprite | C27: Solari Tower guard | D27: P1 Act III, P2 Act III | E27: P2 - Part One | F27: 48x72/frame · 192x288 sheet (4x4) | G27: 2 variants | H27: HD pixel art character sprite sheet for a top-down 2D dark-fantasy RPG (Zelda: Minish Cap fidelity, 48x72 px per frame). Grid layout: 4 rows = walk down / up / left / right, exactly 4 frames per row (walk cycle: contact-pass-contact-pass), 4 rows only, no extra columns. Tower of Celestial Harmony guard: gilded ceremonial half-plate, sun-disc shield, spear. Solari (sun elf) palette: radiant gold, ivory, white marble, dawn-orange accents. Clean readable silhouette, crisp pixel clusters, no anti-aliasing, unified palette, flat solid magenta background for easy removal. | I27: Not Started | K27: Shared across both parts - build once.
A28: CH-027 | B28: Character Sprite | C28: Astra'Thalas citizen set | D28: P1 Act III, P2 Act III | E28: P2 - Part One | F28: 48x72/frame · 192x288 sheet (4x4) | G28: 3 variants | H28: HD pixel art character sprite sheet for a top-down 2D dark-fantasy RPG (Zelda: Minish Cap fidelity, 48x72 px per frame). Grid layout: 4 rows = walk down / up / left / right, exactly 4 frames per row (walk cycle: contact-pass-contact-pass), 4 rows only, no extra columns. Solari capital citizens in festival dress for the solstice. Solari (sun elf) palette: radiant gold, ivory, white marble, dawn-orange accents. Clean readable silhouette, crisp pixel clusters, no anti-aliasing, unified palette, flat solid magenta background for easy removal. | I28: Not Started
A29: CH-028 | B29: Character Sprite | C29: Ashpile child | D29: P2 Act I | E29: P3 - Part Two | F29: 48x72/frame · 192x288 sheet (4x4) | G29: 2 variants | H29: HD pixel art character sprite sheet for a top-down 2D dark-fantasy RPG (Zelda: Minish Cap fidelity, 48x72 px per frame). Grid layout: 4 rows = walk down / up / left / right, exactly 4 frames per row (walk cycle: contact-pass-contact-pass), 4 rows only, no extra columns. Orc children of the birth-camp: small, quick, ragged, resilient. orc/Ashpile palette: ash grey, iron, rust, ember orange. Clean readable silhouette, crisp pixel clusters, no anti-aliasing, unified palette, flat solid magenta background for easy removal. | I29: Not Started
A30: PO-001 | B30: Portrait | C30: Elorin — composed | D30: P1 | E30: P1 - Vertical Slice | F30: 512x512 source -> 96x96 in-game | G30: Expressions: neutral / strained / grieved | H30: Painted character portrait for RPG dialogue UI: bust framing, three-quarter view, dark-fantasy oil-painting style in the tradition of classic CRPG portraits, dramatic single-source lighting, plain very dark background, square composition. A Noctari night elf woman archmage in mid-life: sharp intelligent features, long dark hair, layered indigo academy robes with void-black trim, quiet authority and buried doubt in the eyes. Noctari (night elf) palette: deep indigo, violet, silver starlight accents. | I30: Generated | K30: Keep one style seed/reference across ALL portraits.
A31: PO-002 | B31: Portrait | C31: Grakkar — young | D31: P2 | E31: P3 - Part Two | F31: 512x512 source -> 96x96 in-game | G31: Expressions: guarded / defiant | H31: Painted character portrait for RPG dialogue UI: bust framing, three-quarter view, dark-fantasy oil-painting style in the tradition of classic CRPG portraits, dramatic single-source lighting, plain very dark background, square composition. A young orc slave with watchful, fiercely intelligent eyes, iron collar, ash-dusted skin, unbroken pride. orc/Ashpile palette: ash grey, iron, rust, ember orange. | I31: Not Started | K31: Keep one style seed/reference across ALL portraits.
A32: PO-003 | B32: Portrait | C32: Grakkar — the Unbound | D32: P2 | E32: P3 - Part Two | F32: 512x512 source -> 96x96 in-game | G32: Expressions: resolute / grieving / terrible | H32: Painted character portrait for RPG dialogue UI: bust framing, three-quarter view, dark-fantasy oil-painting style in the tradition of classic CRPG portraits, dramatic single-source lighting, plain very dark background, square composition. An elder orc revolutionary: grey-streaked hair, old scars, eyes that have carried a plan for two centuries. Ash and ember palette. | I32: Not Started | K32: Keep one style seed/reference across ALL portraits.
A33: PO-004 | B33: Portrait | C33: Talindir — apprentice | D33: Cold Open, P1 | E33: P1 - Vertical Slice | F33: 512x512 source -> 96x96 in-game | G33: Expressions: eager / uneasy | H33: Painted character portrait for RPG dialogue UI: bust framing, three-quarter view, dark-fantasy oil-painting style in the tradition of classic CRPG portraits, dramatic single-source lighting, plain very dark background, square composition. A youthful elf scribe with ink-stained fingers and earnest eyes, grey-blue modest robes. | I33: Generated | K33: Keep one style seed/reference across ALL portraits.
A34: PO-005 | B34: Portrait | C34: Talindir — chronicler | D34: Cold Open, Coda | E34: P1 - Vertical Slice | F34: 512x512 source -> 96x96 in-game | G34: Expressions: hollowed / resolved | H34: Painted character portrait for RPG dialogue UI: bust framing, three-quarter view, dark-fantasy oil-painting style in the tradition of classic CRPG portraits, dramatic single-source lighting, plain very dark background, square composition. The same elf scribe aged by catastrophe: gaunt, haunted, holding a ledger like a wound. | I34: Generated | K34: Keep one style seed/reference across ALL portraits.
A35: PO-006 | B35: Portrait | C35: Sera | D35: P1 | E35: P1 - Vertical Slice | F35: 512x512 source -> 96x96 in-game | G35: Expressions: precise / warm (rare) | H35: Painted character portrait for RPG dialogue UI: bust framing, three-quarter view, dark-fantasy oil-painting style in the tradition of classic CRPG portraits, dramatic single-source lighting, plain very dark background, square composition. A Solari sun elf enchantress: immaculate, geometric gold jewelry, appraising gaze. Solari (sun elf) palette: radiant gold, ivory, white marble, dawn-orange accents. | I35: Generated | K35: Keep one style seed/reference across ALL portraits.
A36: PO-007 | B36: Portrait | C36: Coil | D36: P1 | E36: P1 - Vertical Slice | F36: 512x512 source -> 96x96 in-game | G36: Expressions: animated / anxious | H36: Painted character portrait for RPG dialogue UI: bust framing, three-quarter view, dark-fantasy oil-painting style in the tradition of classic CRPG portraits, dramatic single-source lighting, plain very dark background, square composition. A wiry Noctari theorist with spectacles, ink smudges, and the face of a man who sees the mathematics before the consequences. | I36: Generated | K36: Keep one style seed/reference across ALL portraits.
A37: PO-008 | B37: Portrait | C37: Vara | D37: P1 | E37: P1 - Vertical Slice | F37: 512x512 source -> 96x96 in-game | G37: Expressions: bright / wounded | H37: Painted character portrait for RPG dialogue UI: bust framing, three-quarter view, dark-fantasy oil-painting style in the tradition of classic CRPG portraits, dramatic single-source lighting, plain very dark background, square composition. A young human woman among elves: open face, quick eyes, plain clothes, quietly aware she must be twice as good. | I37: Generated | K37: Keep one style seed/reference across ALL portraits.
A38: PO-009 | B38: Portrait | C38: Durak Ironthought | D38: P1 | E38: P2 - Part One | F38: 512x512 source -> 96x96 in-game | G38: Expressions: dry / grave | H38: Painted character portrait for RPG dialogue UI: bust framing, three-quarter view, dark-fantasy oil-painting style in the tradition of classic CRPG portraits, dramatic single-source lighting, plain very dark background, square composition. A stout Terran geomancer: stone-grey skin, copper-ringed beard, patient mountain-deep eyes. | I38: Not Started | K38: Keep one style seed/reference across ALL portraits.
A39: PO-010 | B39: Portrait | C39: Seravin Hollow-Water | D39: P1 memories | E39: P2 - Part One | F39: 512x512 source -> 96x96 in-game | G39: Expressions: serene | H39: Painted character portrait for RPG dialogue UI: bust framing, three-quarter view, dark-fantasy oil-painting style in the tradition of classic CRPG portraits, dramatic single-source lighting, plain very dark background, square composition. An elderly Noctari mentor, serene as still water, fading blue robes, kindness with edges. | I39: Not Started | K39: Keep one style seed/reference across ALL portraits.
A40: PO-011 | B40: Portrait | C40: Corel | D40: P1 | E40: P2 - Part One | F40: 512x512 source -> 96x96 in-game | G40: Expressions: exhausted / alarmed | H40: Painted character portrait for RPG dialogue UI: bust framing, three-quarter view, dark-fantasy oil-painting style in the tradition of classic CRPG portraits, dramatic single-source lighting, plain very dark background, square composition. An exhausted Noctari archmagister: dark-ringed eyes, formal collar askew, decency worn thin by duty. | I40: Not Started | K40: Keep one style seed/reference across ALL portraits.
A41: PO-012 | B41: Portrait | C41: Morga Steelheart | D41: P2 | E41: P3 - Part Two | F41: 512x512 source -> 96x96 in-game | G41: Expressions: stern / sorrowing | H41: Painted character portrait for RPG dialogue UI: bust framing, three-quarter view, dark-fantasy oil-painting style in the tradition of classic CRPG portraits, dramatic single-source lighting, plain very dark background, square composition. An orc matriarch elder: iron-grey braids, judge's gaze, the revolution's conscience made flesh. | I41: Not Started | K41: Keep one style seed/reference across ALL portraits.
... A59: EN-016 | B59: Environment | C59: The Same Night — city backdrops | D59: Cold Open | E59: P1 - Vertical Slice | F59: 32px tileset sheet | G59: - | H59: HD pixel art environment tileset reference sheet for a top-down 2D RPG, strict 32 px grid, Zelda: Minish Cap fidelity, dark fantasy. Astra'Thalas at the moment magic dies: festival lights guttering out street by street, panic in gold avenues, the Tower dark against a starless sky. Sheet must include: ground/floor tiles, wall tiles with edge and corner pieces, and 8-10 signature props for the location, arranged neatly on a grid, unified palette, no anti-aliasing. | I59: Generated | K59: Generate as reference sheet; rebuild clean tiles over it in Affinity (see AFFINITY PIPELINE).
A60: PR-001 | B60: Prop / Object | C60: The Nullstone — prototype | D60: P1 Act II | E60: P2 - Part One | F60: 32px grid multiples | G60: States noted in description | H60: HD pixel art object sprite for a top-down 2D RPG, 32 px grid scale, dark fantasy, clean silhouette, unified palette, no anti-aliasing, flat solid magenta background. A rough-hewn obsidian-like stone the size of a heart, half-caged in a brass calibration frame, faint unlight seams. Hero prop. | I60: Not Started
A61: PR-002 | B61: Prop / Object | C61: The Nullstone — complete | D61: P1 A3, P2 A3 | E61: P2 - Part One | F61: 32px grid multiples | G61: States noted in description | H61: HD pixel art object sprite for a top-down 2D RPG, 32 px grid scale, dark fantasy, clean silhouette, unified palette, no anti-aliasing, flat solid magenta background. A perfect seamless black stone that seems to drink light, resting on a warded dais. THE central object of the franchise - iconic, simple, wrong-feeling. | I61: Not Started
A62: PR-003 | B62: Prop / Object | C62: The Nullstone — activated | D62: P2 Act III | E62: P3 - Part Two | F62: 32px grid multiples | G62: States noted in description | H62: HD pixel art object sprite for a top-down 2D RPG, 32 px grid scale, dark fantasy, clean silhouette, unified palette, no anti-aliasing, flat solid magenta background. The same black stone erupting with expanding rings of un-light: colors dying outward from it in bands. Frame for the activation moment. | I62: Not Started
A63: PR-004 | B63: Prop / Object | C63: Containment rig set | D63: P1 | E63: P1 - Vertical Slice | F63: 32px grid multiples | G63: States noted in description | H63: HD pixel art object sprite for a top-down 2D RPG, 32 px grid scale, dark fantasy, clean silhouette, unified palette, no anti-aliasing, flat solid magenta background. Arcane lab apparatus: crystal capacitor stacks, brass armature frames, glyph projectors, cable-vines of silver wire. 5-6 pieces. | I63: Generated
A64: PR-005 | B64: Prop / Object | C64: Aether Ring display | D64: Both parts | E64: P2 - Part One | F64: 32px grid multiples | G64: States noted in description | H64: HD pixel art object sprite for a top-down 2D RPG, 32 px grid scale, dark fantasy, clean silhouette, unified palette, no anti-aliasing, flat solid magenta background. A ring pedestal displaying a bonded Aether Ring: slim band with a live essence gem, under rune-glass. | I64: Not Started
A65: PR-006 | B65: Prop / Object | C65: Essence crystal set | D65: Both parts | E65: P2 - Part One | F65: 32px grid multiples | G65: States noted in description | H65: HD pixel art object sprite for a top-down 2D RPG, 32 px grid scale, dark fantasy, clean silhouette, unified palette, no anti-aliasing, flat solid magenta background. 6 essence crystals in distinct colors (ember, tide, stone, gale, shade, radiant), raw and socketed variants. | I65: Not Started
A66: PR-007 | B66: Prop / Object | C66: Bookshelf & scroll rack set | D66: P1, P2 | E66: P1 - Vertical Slice | F66: 32px grid multiples | G66: States noted in description | H66: HD pixel art object sprite for a top-down 2D RPG, 32 px grid scale, dark fantasy, clean silhouette, unified palette, no anti-aliasing, flat solid magenta background. Library furniture: tall shelves (full/half-empty), scroll pigeonhole racks, rolling ladder, reading lectern, book stacks. | I66: Generated
A67: PR-008 | B67: Prop / Object | C67: Documents set (world sprites) | D67: Both parts | E67: P1 - Vertical Slice | F67: 32px grid multiples | G67: States noted in description | H67: HD pixel art object sprite for a top-down 2D RPG, 32 px grid scale, dark fantasy, clean silhouette, unified palette, no anti-aliasing, flat solid magenta background. Placeable paper props: single scroll, opened letter, bound journal, schematic sheet, ledger, sealed envelope, burnt fragment. | I67: Generated
A68: PR-009 | B68: Prop / Object | C68: Elorin's journal (hero prop) | D68: Both parts | E68: P2 - Part One | F68: 32px grid multiples | G68: States noted in description | H68: HD pixel art object sprite for a top-down 2D RPG, 32 px grid scale, dark fantasy, clean silhouette, unified palette, no anti-aliasing, flat solid magenta background. A distinctive indigo-bound journal with a silver void-glyph clasp - must read at 32px. Appears in both centuries. | I68: Not Started
A69: PR-010 | B69: Prop / Object | C69: Safeguard schematic (hero prop) | D69: Both parts | E69: P2 - Part One | F69: 32px grid multiples | G69: States noted in description | H69: HD pixel art object sprite for a top-down 2D RPG, 32 px grid scale, dark fantasy, clean silhouette, unified palette, no anti-aliasing, flat solid magenta background. A large unrolled vault schematic: three concentric ward-ring designs, annotated margins. The Legacy System's key document. | I69: Not Started
A70: PR-011 | B70: Prop / Object | C70: Orc machine — crystal furnace | D70: P2 | E70: P3 - Part Two | F70: 32px grid multiples | G70: States noted in description | H70: HD pixel art object sprite for a top-down 2D RPG, 32 px grid scale, dark fantasy, clean silhouette, unified palette, no anti-aliasing, flat solid magenta background. An arcano-industrial furnace: iron bulk, crystal fire-heart, chain feeds, glyph pressure dials, soot staining. | I70: Not Started
A71: PR-012 | B71: Prop / Object | C71: Orc machine — ore lift & hoist | D71: P2 | E71: P3 - Part Two | F71: 32px grid multiples | G71: States noted in description | H71: HD pixel art object sprite for a top-down 2D RPG, 32 px grid scale, dark fantasy, clean silhouette, unified palette, no anti-aliasing, flat solid magenta background. Chain-driven ore lift: winch drum, counterweights, hanging cage platform, hand-crank station. | I71: Not Started
... A110: UI-011 | B110: UI | C110: Main menu key art | D110: Global | E110: P2 - Part One | F110: PNG @2x, transparent | G110: - | H110: 2D RPG user-interface element, dark-fantasy illuminated-manuscript aesthetic: aged parchment textures, deep indigo and antique gold accents, subtle arcane filigree, clean edges that scale well, flat solid background. Key art: the Tower of Celestial Harmony silhouetted at the instant the lights die - one half of the sky festival-gold, the other starless black, a tiny figure at the base. | I110: Not Started
A111: UI-012 | B111: UI | C111: Title logo — KAYOS: The Night of Silence | D111: Global | E111: P2 - Part One | F111: PNG @2x, transparent | G111: - | H111: 2D RPG user-interface element, dark-fantasy illuminated-manuscript aesthetic: aged parchment textures, deep indigo and antique gold accents, subtle arcane filigree, clean edges that scale well, flat solid background. A game logo: the word KAYOS in bold carved-stone serif capitals with a hairline gold inlay, subtitle 'The Night of Silence' in elegant elven-flavored script beneath, on transparent background. | I111: Not Started | K111: Also deliver monochrome variant.
A112: UI-013 | B112: UI | C112: Act / era title cards | D112: Global | E112: P2 - Part One | F112: PNG @2x, transparent | G112: 6 cards | H112: 2D RPG user-interface element, dark-fantasy illuminated-manuscript aesthetic: aged parchment textures, deep indigo and antique gold accents, subtle arcane filigree, clean edges that scale well, flat solid background. Six full-width chapter title plates in illuminated-manuscript style with era dates, ornamental rules, small central glyph. | I112: Not Started
A113: UI-014 | B113: UI | C113: Save/load slot cards | D113: Global | E113: P3 - Part Two | F113: PNG @2x, transparent | G113: - | H113: 2D RPG user-interface element, dark-fantasy illuminated-manuscript aesthetic: aged parchment textures, deep indigo and antique gold accents, subtle arcane filigree, clean edges that scale well, flat solid background. Save slot cards styled as wax-sealed chronicle pages with thumbnail window and date line. | I113: Not Started
A114: UI-015 | B114: UI | C114: Cursor & indicator set | D114: Global | E114: P2 - Part One | F114: PNG @2x, transparent | G114: cursor / talk / examine / take / exit | H114: 2D RPG user-interface element, dark-fantasy illuminated-manuscript aesthetic: aged parchment textures, deep indigo and antique gold accents, subtle arcane filigree, clean edges that scale well, flat solid background. A small interaction icon set, single-color with gold accent, readable at 16px. | I114: Not Started
A115: UI-016 | B115: UI | C115: Settings & system icons | D115: Global | E115: P3 - Part Two | F115: PNG @2x, transparent | G115: 8-10 icons | H115: 2D RPG user-interface element, dark-fantasy illuminated-manuscript aesthetic: aged parchment textures, deep indigo and antique gold accents, subtle arcane filigree, clean edges that scale well, flat solid background. Small UI icon set: gear, speaker, music note, window, keyboard, question, back arrow, quit door - consistent stroke. | I115: Not Started
A116: UI-017 | B116: UI | C116: Vision transition overlay | D116: Global | E116: P3 - Part Two | F116: PNG @2x, transparent | G116: - | H116: 2D RPG user-interface element, dark-fantasy illuminated-manuscript aesthetic: aged parchment textures, deep indigo and antique gold accents, subtle arcane filigree, clean edges that scale well, flat solid background. A screen-edge vignette overlay of creeping star-void and drifting glyph fragments, for entering crossing-point visions. | I116: Not Started
A117: UI-018 | B117: UI | C117: Toast / notification chips | D117: Global | E117: P3 - Part Two | F117: PNG @2x, transparent | G117: quest / item / legacy flag | H117: 2D RPG user-interface element, dark-fantasy illuminated-manuscript aesthetic: aged parchment textures, deep indigo and antique gold accents, subtle arcane filigree, clean edges that scale well, flat solid background. Three small notification chips: quest quill, item satchel, and a distinct 'the ledger remembers' seal for Legacy flags. | I117: Not Started
A118: VS-001 | B118: Story Panel | C118: Cold Open — the lights die | D118: Cold Open | E118: P1 - Vertical Slice | F118: 1920x1080 (16:9) | G118: - | H118: Full-screen illustrated story panel for a dark-fantasy RPG: painterly digital art, cinematic composition, moody volumetric lighting, 16:9 aspect. From a high balcony of a gold festival city at night, lights are going out district by district in a spreading wave toward the viewer; a young elf scribe grips the rail, ledger under one arm. | I118: Generated | K118: Painterly, NOT pixel art - deliberate register shift for visions.
A119: VS-002 | B119: Story Panel | C119: Crossing Point — the glance | D119: P1 & P2 | E119: P2 - Part One | F119: 1920x1080 (16:9) | G119: - | H119: Full-screen illustrated story panel for a dark-fantasy RPG: painterly digital art, cinematic composition, moody volumetric lighting, 16:9 aspect. A crowded elven facility hall: a robed Noctari woman and a young collared orc laborer lock eyes for one second across the crowd - everything else soft, the sightline sharp. | I119: Not Started | K119: Painterly, NOT pixel art - deliberate register shift for visions.
A120: VS-003 | B120: Story Panel | C120: Crossing Point — the reader | D120: P2 | E120: P3 - Part Two | F120: 1920x1080 (16:9) | G120: - | H120: Full-screen illustrated story panel for a dark-fantasy RPG: painterly digital art, cinematic composition, moody volumetric lighting, 16:9 aspect. Deep archive alcove at lantern-light: a massive orc hunched over a small indigo journal, one finger under a line of elven script, tears or fury held at the jaw - ambiguous. | I120: Not Started | K120: Painterly, NOT pixel art - deliberate register shift for visions.
A121: VS-004 | B121: Story Panel | C121: Crossing Point — the Same Night (Elorin side) | D121: P1 | E121: P2 - Part One | F121: 1920x1080 (16:9) | G121: - | H121: Full-screen illustrated story panel for a dark-fantasy RPG: painterly digital art, cinematic composition, moody volumetric lighting, 16:9 aspect. A distant coastline at night: an exiled elven woman turns at the moment the horizon's city-glow behind her simply stops. | I121: Not Started | K121: Painterly, NOT pixel art - deliberate register shift for visions.
A122: VS-005 | B122: Story Panel | C122: Crossing Point — the Same Night (Grakkar side) | D122: P2 | E122: P3 - Part Two | F122: 1920x1080 (16:9) | G122: - | H122: Full-screen illustrated story panel for a dark-fantasy RPG: painterly digital art, cinematic composition, moody volumetric lighting, 16:9 aspect. Inside the vault: an orc's scarred hand resting on a ringed black rod seated in a dais, ward-rings dying around him like settling dust, his face lit from below by the last light in the world. | I122: Not Started | K122: Painterly, NOT pixel art - deliberate register shift for visions.
A123: VS-006 | B123: Story Panel | C123: Northreach — the Tear | D123: P1 | E123: P2 - Part One | F123: 1920x1080 (16:9) | G123: - | H123: Full-screen illustrated story panel for a dark-fantasy RPG: painterly digital art, cinematic composition, moody volumetric lighting, 16:9 aspect. A northern town split by a wound in the air itself: raw wild magic pouring upward like an inverted waterfall, tiny figures fleeing, snow burning. | I123: Not Started | K123: Painterly, NOT pixel art - deliberate register shift for visions.
A124: VS-007 | B124: Story Panel | C124: Black Crag falls | D124: P2 | E124: P3 - Part Two | F124: 1920x1080 (16:9) | G124: - | H124: Full-screen illustrated story panel for a dark-fantasy RPG: painterly digital art, cinematic composition, moody volumetric lighting, 16:9 aspect. A basalt crag fortress at dusk under arcane bombardment: broken-chain banners burning, a line of orc silhouettes holding a gate that will not hold. | I124: Not Started | K124: Painterly, NOT pixel art - deliberate register shift for visions.
A125: VS-008 | B125: Story Panel | C125: Legacy ending — The Buried Truth | D125: Coda | E125: P3 - Part Two | F125: 1920x1080 (16:9) | G125: - | H125: Full-screen illustrated story panel for a dark-fantasy RPG: painterly digital art, cinematic composition, moody volumetric lighting, 16:9 aspect. A moonlit scriptorium: an aged elf scribe lowering a thick chronicle into an iron document chest, lamplight on his face, the sea grey beyond the window. | I125: Not Started | K125: Painterly, NOT pixel art - deliberate register shift for visions.
A126: VS-009 | B126: Story Panel | C126: Legacy ending — The Open Wound | D126: Coda | E126: P4 - Polish | F126: 1920x1080 (16:9) | G126: - | H126: Full-screen illustrated story panel for a dark-fantasy RPG: painterly digital art, cinematic composition, moody volumetric lighting, 16:9 aspect. A ruined city square: crowds gathered around posted broadsheets, faces lit by torch-light, grief and rage in equal measure. | I126: Not Started | K126: Painterly, NOT pixel art - deliberate register shift for visions.
A127: VS-010 | B127: Story Panel | C127: Legacy ending — The Kind Lie | D127: Coda | E127: P4 - Polish | F127: 1920x1080 (16:9) | G127: - | H127: Full-screen illustrated story panel for a dark-fantasy RPG: painterly digital art, cinematic composition, moody volumetric lighting, 16:9 aspect. A quiet schoolroom years later: children reciting from a tidy history book while, out the window, a shrouded statue is unveiled to polite applause. | I127: Not Started | K127: Painterly, NOT pixel art - deliberate register shift for visions.
A128: FN-001 | B128: Font / External | C128: Dialogue & body font | D128: Global | E128: P1 - Vertical Slice | F128: TTF, pixel font | G128: - | H128: NOT GENERATED - source a free pixel font suited to 640x360 (suggested: 'm5x7' or 'Pixel Operator', both free). Verify license permits games. | I128: Generated | K128: Test readability at native resolution before committing.
A129: FN-002 | B129: Font / External | C129: Title & header font | D129: Global | E129: P2 - Part One | F129: TTF | G129: - | H129: NOT GENERATED - source a fantasy display pixel font (suggested: 'Alagard', free). Verify license. | I129: Not Started
A130: FN-003 | B130: Font / External | C130: Ambient audio & music | D130: Global | E130: P4 - Polish | F130: OGG | G130: - | H130: NOT GENERATED HERE - placeholder row so audio is tracked; source from free libraries or commission later. | I130: Not Started | K130: Out of scope for image gen; tracked for completeness.
A131: EN-019 | B131: Environment | C131: Astra'Thalas - the scriptorium (Cold Open) | D131: Cold Open | E131: P1 - Vertical Slice | F131: 32x32 tiles + props | G131: Floor, wall, window, desk, cold cup. Lit and unlit states for the Silence. | H131: HD pixel art top-down interior for a dark-fantasy RPG. The record scriptorium of an elven astral archive at night, directly below a festival balcony. Ranked scroll racks along the back wall, reading desks, a tall window showing the lit festival city beyond, an indigo lacquered locked cabinet. Cold, orderly, deserted - everyone has gone to the festival. Lit only by a reading lamp and the gold spill through the window. Muted Noctari indigo, grey stone, parchment, aged wood. 32x32 tile grid. | I131: Placeholder | K131: NEW 2026-07-17. The room below the Cold Open stair. EN-017/018 were already claimed by the Starfall and Umbraveil map prompts, so this took the next free id. Currently a labelled placeholder in godot/art/placeholders/EN-019_*.png.
